[
    {
        "name": "Bulbasaur",
        "pokedex_number": "1",
        "experience_growth": "1059860"
    },
    {
        "name": "Ivysaur",
        "pokedex_number": "2",
        "experience_growth": "1059860"
    },
    {
        "name": "Venusaur",
        "pokedex_number": "3",
        "experience_growth": "1059860"
    },
    {
        "name": "Charmander",
        "pokedex_number": "4",
        "experience_growth": "1059860"
    },
    {
        "name": "Charmeleon",
        "pokedex_number": "5",
        "experience_growth": "1059860"
    },
    {
        "name": "Charizard",
        "pokedex_number": "6",
        "experience_growth": "1059860"
    },
    {
        "name": "Squirtle",
        "pokedex_number": "7",
        "experience_growth": "1059860"
    },
    {
        "name": "Wartortle",
        "pokedex_number": "8",
        "experience_growth": "1059860"
    },
    {
        "name": "Blastoise",
        "pokedex_number": "9",
        "experience_growth": "1059860"
    },
    {
        "name": "Caterpie",
        "pokedex_number": "10",
        "experience_growth": "1000000"
    },
    {
        "name": "Metapod",
        "pokedex_number": "11",
        "experience_growth": "1000000"
    },
    {
        "name": "Butterfree",
        "pokedex_number": "12",
        "experience_growth": "1000000"
    },
    {
        "name": "Weedle",
        "pokedex_number": "13",
        "experience_growth": "1000000"
    },
    {
        "name": "Kakuna",
        "pokedex_number": "14",
        "experience_growth": "1000000"
    },
    {
        "name": "Beedrill",
        "pokedex_number": "15",
        "experience_growth": "1000000"
    },
    {
        "name": "Pidgey",
        "pokedex_number": "16",
        "experience_growth": "1059860"
    },
    {
        "name": "Pidgeotto",
        "pokedex_number": "17",
        "experience_growth": "1059860"
    },
    {
        "name": "Pidgeot",
        "pokedex_number": "18",
        "experience_growth": "1059860"
    },
    {
        "name": "Rattata",
        "pokedex_number": "19",
        "experience_growth": "1000000"
    },
    {
        "name": "Raticate",
        "pokedex_number": "20",
        "experience_growth": "1000000"
    },
    {
        "name": "Spearow",
        "pokedex_number": "21",
        "experience_growth": "1000000"
    },
    {
        "name": "Fearow",
        "pokedex_number": "22",
        "experience_growth": "1000000"
    },
    {
        "name": "Ekans",
        "pokedex_number": "23",
        "experience_growth": "1000000"
    },
    {
        "name": "Arbok",
        "pokedex_number": "24",
        "experience_growth": "1000000"
    },
    {
        "name": "Pikachu",
        "pokedex_number": "25",
        "experience_growth": "1000000"
    },
    {
        "name": "Raichu",
        "pokedex_number": "26",
        "experience_growth": "1000000"
    },
    {
        "name": "Sandshrew",
        "pokedex_number": "27",
        "experience_growth": "1000000"
    },
    {
        "name": "Sandslash",
        "pokedex_number": "28",
        "experience_growth": "1000000"
    },
    {
        "name": "Nidoran\u2640",
        "pokedex_number": "29",
        "experience_growth": "1059860"
    },
    {
        "name": "Nidorina",
        "pokedex_number": "30",
        "experience_growth": "1059860"
    },
    {
        "name": "Nidoqueen",
        "pokedex_number": "31",
        "experience_growth": "1059860"
    },
    {
        "name": "Nidoran\u2642",
        "pokedex_number": "32",
        "experience_growth": "1059860"
    },
    {
        "name": "Nidorino",
        "pokedex_number": "33",
        "experience_growth": "1059860"
    },
    {
        "name": "Nidoking",
        "pokedex_number": "34",
        "experience_growth": "1059860"
    },
    {
        "name": "Clefairy",
        "pokedex_number": "35",
        "experience_growth": "800000"
    },
    {
        "name": "Clefable",
        "pokedex_number": "36",
        "experience_growth": "800000"
    },
    {
        "name": "Vulpix",
        "pokedex_number": "37",
        "experience_growth": "1000000"
    },
    {
        "name": "Ninetales",
        "pokedex_number": "38",
        "experience_growth": "1000000"
    },
    {
        "name": "Jigglypuff",
        "pokedex_number": "39",
        "experience_growth": "800000"
    },
    {
        "name": "Wigglytuff",
        "pokedex_number": "40",
        "experience_growth": "800000"
    },
    {
        "name": "Zubat",
        "pokedex_number": "41",
        "experience_growth": "1000000"
    },
    {
        "name": "Golbat",
        "pokedex_number": "42",
        "experience_growth": "1000000"
    },
    {
        "name": "Oddish",
        "pokedex_number": "43",
        "experience_growth": "1059860"
    },
    {
        "name": "Gloom",
        "pokedex_number": "44",
        "experience_growth": "1059860"
    },
    {
        "name": "Vileplume",
        "pokedex_number": "45",
        "experience_growth": "1059860"
    },
    {
        "name": "Paras",
        "pokedex_number": "46",
        "experience_growth": "1000000"
    },
    {
        "name": "Parasect",
        "pokedex_number": "47",
        "experience_growth": "1000000"
    },
    {
        "name": "Venonat",
        "pokedex_number": "48",
        "experience_growth": "1000000"
    },
    {
        "name": "Venomoth",
        "pokedex_number": "49",
        "experience_growth": "1000000"
    },
    {
        "name": "Diglett",
        "pokedex_number": "50",
        "experience_growth": "1000000"
    },
    {
        "name": "Dugtrio",
        "pokedex_number": "51",
        "experience_growth": "1000000"
    },
    {
        "name": "Meowth",
        "pokedex_number": "52",
        "experience_growth": "1000000"
    },
    {
        "name": "Persian",
        "pokedex_number": "53",
        "experience_growth": "1000000"
    },
    {
        "name": "Psyduck",
        "pokedex_number": "54",
        "experience_growth": "1000000"
    },
    {
        "name": "Golduck",
        "pokedex_number": "55",
        "experience_growth": "1000000"
    },
    {
        "name": "Mankey",
        "pokedex_number": "56",
        "experience_growth": "1000000"
    },
    {
        "name": "Primeape",
        "pokedex_number": "57",
        "experience_growth": "1000000"
    },
    {
        "name": "Growlithe",
        "pokedex_number": "58",
        "experience_growth": "1250000"
    },
    {
        "name": "Arcanine",
        "pokedex_number": "59",
        "experience_growth": "1250000"
    },
    {
        "name": "Poliwag",
        "pokedex_number": "60",
        "experience_growth": "1059860"
    },
    {
        "name": "Poliwhirl",
        "pokedex_number": "61",
        "experience_growth": "1059860"
    },
    {
        "name": "Poliwrath",
        "pokedex_number": "62",
        "experience_growth": "1059860"
    },
    {
        "name": "Abra",
        "pokedex_number": "63",
        "experience_growth": "1059860"
    },
    {
        "name": "Kadabra",
        "pokedex_number": "64",
        "experience_growth": "1059860"
    },
    {
        "name": "Alakazam",
        "pokedex_number": "65",
        "experience_growth": "1059860"
    },
    {
        "name": "Machop",
        "pokedex_number": "66",
        "experience_growth": "1059860"
    },
    {
        "name": "Machoke",
        "pokedex_number": "67",
        "experience_growth": "1059860"
    },
    {
        "name": "Machamp",
        "pokedex_number": "68",
        "experience_growth": "1059860"
    },
    {
        "name": "Bellsprout",
        "pokedex_number": "69",
        "experience_growth": "1059860"
    },
    {
        "name": "Weepinbell",
        "pokedex_number": "70",
        "experience_growth": "1059860"
    },
    {
        "name": "Victreebel",
        "pokedex_number": "71",
        "experience_growth": "1059860"
    },
    {
        "name": "Tentacool",
        "pokedex_number": "72",
        "experience_growth": "1250000"
    },
    {
        "name": "Tentacruel",
        "pokedex_number": "73",
        "experience_growth": "1250000"
    },
    {
        "name": "Geodude",
        "pokedex_number": "74",
        "experience_growth": "1059860"
    },
    {
        "name": "Graveler",
        "pokedex_number": "75",
        "experience_growth": "1059860"
    },
    {
        "name": "Golem",
        "pokedex_number": "76",
        "experience_growth": "1059860"
    },
    {
        "name": "Ponyta",
        "pokedex_number": "77",
        "experience_growth": "1000000"
    },
    {
        "name": "Rapidash",
        "pokedex_number": "78",
        "experience_growth": "1000000"
    },
    {
        "name": "Slowpoke",
        "pokedex_number": "79",
        "experience_growth": "1000000"
    },
    {
        "name": "Slowbro",
        "pokedex_number": "80",
        "experience_growth": "1000000"
    },
    {
        "name": "Magnemite",
        "pokedex_number": "81",
        "experience_growth": "1000000"
    },
    {
        "name": "Magneton",
        "pokedex_number": "82",
        "experience_growth": "1000000"
    },
    {
        "name": "Farfetch'd",
        "pokedex_number": "83",
        "experience_growth": "1000000"
    },
    {
        "name": "Doduo",
        "pokedex_number": "84",
        "experience_growth": "1000000"
    },
    {
        "name": "Dodrio",
        "pokedex_number": "85",
        "experience_growth": "1000000"
    },
    {
        "name": "Seel",
        "pokedex_number": "86",
        "experience_growth": "1000000"
    },
    {
        "name": "Dewgong",
        "pokedex_number": "87",
        "experience_growth": "1000000"
    },
    {
        "name": "Grimer",
        "pokedex_number": "88",
        "experience_growth": "1000000"
    },
    {
        "name": "Muk",
        "pokedex_number": "89",
        "experience_growth": "1000000"
    },
    {
        "name": "Shellder",
        "pokedex_number": "90",
        "experience_growth": "1250000"
    },
    {
        "name": "Cloyster",
        "pokedex_number": "91",
        "experience_growth": "1250000"
    },
    {
        "name": "Gastly",
        "pokedex_number": "92",
        "experience_growth": "1059860"
    },
    {
        "name": "Haunter",
        "pokedex_number": "93",
        "experience_growth": "1059860"
    },
    {
        "name": "Gengar",
        "pokedex_number": "94",
        "experience_growth": "1059860"
    },
    {
        "name": "Onix",
        "pokedex_number": "95",
        "experience_growth": "1000000"
    },
    {
        "name": "Drowzee",
        "pokedex_number": "96",
        "experience_growth": "1000000"
    },
    {
        "name": "Hypno",
        "pokedex_number": "97",
        "experience_growth": "1000000"
    },
    {
        "name": "Krabby",
        "pokedex_number": "98",
        "experience_growth": "1000000"
    },
    {
        "name": "Kingler",
        "pokedex_number": "99",
        "experience_growth": "1000000"
    },
    {
        "name": "Voltorb",
        "pokedex_number": "100",
        "experience_growth": "1000000"
    },
    {
        "name": "Electrode",
        "pokedex_number": "101",
        "experience_growth": "1000000"
    },
    {
        "name": "Exeggcute",
        "pokedex_number": "102",
        "experience_growth": "1250000"
    },
    {
        "name": "Exeggutor",
        "pokedex_number": "103",
        "experience_growth": "1250000"
    },
    {
        "name": "Cubone",
        "pokedex_number": "104",
        "experience_growth": "1000000"
    },
    {
        "name": "Marowak",
        "pokedex_number": "105",
        "experience_growth": "1000000"
    },
    {
        "name": "Hitmonlee",
        "pokedex_number": "106",
        "experience_growth": "1000000"
    },
    {
        "name": "Hitmonchan",
        "pokedex_number": "107",
        "experience_growth": "1000000"
    },
    {
        "name": "Lickitung",
        "pokedex_number": "108",
        "experience_growth": "1000000"
    },
    {
        "name": "Koffing",
        "pokedex_number": "109",
        "experience_growth": "1000000"
    },
    {
        "name": "Weezing",
        "pokedex_number": "110",
        "experience_growth": "1000000"
    },
    {
        "name": "Rhyhorn",
        "pokedex_number": "111",
        "experience_growth": "1250000"
    },
    {
        "name": "Rhydon",
        "pokedex_number": "112",
        "experience_growth": "1250000"
    },
    {
        "name": "Chansey",
        "pokedex_number": "113",
        "experience_growth": "800000"
    },
    {
        "name": "Tangela",
        "pokedex_number": "114",
        "experience_growth": "1000000"
    },
    {
        "name": "Kangaskhan",
        "pokedex_number": "115",
        "experience_growth": "1000000"
    },
    {
        "name": "Horsea",
        "pokedex_number": "116",
        "experience_growth": "1000000"
    },
    {
        "name": "Seadra",
        "pokedex_number": "117",
        "experience_growth": "1000000"
    },
    {
        "name": "Goldeen",
        "pokedex_number": "118",
        "experience_growth": "1000000"
    },
    {
        "name": "Seaking",
        "pokedex_number": "119",
        "experience_growth": "1000000"
    },
    {
        "name": "Staryu",
        "pokedex_number": "120",
        "experience_growth": "1250000"
    },
    {
        "name": "Starmie",
        "pokedex_number": "121",
        "experience_growth": "1250000"
    },
    {
        "name": "Mr. Mime",
        "pokedex_number": "122",
        "experience_growth": "1000000"
    },
    {
        "name": "Scyther",
        "pokedex_number": "123",
        "experience_growth": "1000000"
    },
    {
        "name": "Jynx",
        "pokedex_number": "124",
        "experience_growth": "1000000"
    },
    {
        "name": "Electabuzz",
        "pokedex_number": "125",
        "experience_growth": "1000000"
    },
    {
        "name": "Magmar",
        "pokedex_number": "126",
        "experience_growth": "1000000"
    },
    {
        "name": "Pinsir",
        "pokedex_number": "127",
        "experience_growth": "1250000"
    },
    {
        "name": "Tauros",
        "pokedex_number": "128",
        "experience_growth": "1250000"
    },
    {
        "name": "Magikarp",
        "pokedex_number": "129",
        "experience_growth": "1250000"
    },
    {
        "name": "Gyarados",
        "pokedex_number": "130",
        "experience_growth": "1250000"
    },
    {
        "name": "Lapras",
        "pokedex_number": "131",
        "experience_growth": "1250000"
    },
    {
        "name": "Ditto",
        "pokedex_number": "132",
        "experience_growth": "1000000"
    },
    {
        "name": "Eevee",
        "pokedex_number": "133",
        "experience_growth": "1000000"
    },
    {
        "name": "Vaporeon",
        "pokedex_number": "134",
        "experience_growth": "1000000"
    },
    {
        "name": "Jolteon",
        "pokedex_number": "135",
        "experience_growth": "1000000"
    },
    {
        "name": "Flareon",
        "pokedex_number": "136",
        "experience_growth": "1000000"
    },
    {
        "name": "Porygon",
        "pokedex_number": "137",
        "experience_growth": "1000000"
    },
    {
        "name": "Omanyte",
        "pokedex_number": "138",
        "experience_growth": "1000000"
    },
    {
        "name": "Omastar",
        "pokedex_number": "139",
        "experience_growth": "1000000"
    },
    {
        "name": "Kabuto",
        "pokedex_number": "140",
        "experience_growth": "1000000"
    },
    {
        "name": "Kabutops",
        "pokedex_number": "141",
        "experience_growth": "1000000"
    },
    {
        "name": "Aerodactyl",
        "pokedex_number": "142",
        "experience_growth": "1250000"
    },
    {
        "name": "Snorlax",
        "pokedex_number": "143",
        "experience_growth": "1250000"
    },
    {
        "name": "Articuno",
        "pokedex_number": "144",
        "experience_growth": "1250000"
    },
    {
        "name": "Zapdos",
        "pokedex_number": "145",
        "experience_growth": "1250000"
    },
    {
        "name": "Moltres",
        "pokedex_number": "146",
        "experience_growth": "1250000"
    },
    {
        "name": "Dratini",
        "pokedex_number": "147",
        "experience_growth": "1250000"
    },
    {
        "name": "Dragonair",
        "pokedex_number": "148",
        "experience_growth": "1250000"
    },
    {
        "name": "Dragonite",
        "pokedex_number": "149",
        "experience_growth": "1250000"
    },
    {
        "name": "Mewtwo",
        "pokedex_number": "150",
        "experience_growth": "1250000"
    },
    {
        "name": "Mew",
        "pokedex_number": "151",
        "experience_growth": "1059860"
    },
    {
        "name": "Chikorita",
        "pokedex_number": "152",
        "experience_growth": "1059860"
    },
    {
        "name": "Bayleef",
        "pokedex_number": "153",
        "experience_growth": "1059860"
    },
    {
        "name": "Meganium",
        "pokedex_number": "154",
        "experience_growth": "1059860"
    },
    {
        "name": "Cyndaquil",
        "pokedex_number": "155",
        "experience_growth": "1059860"
    },
    {
        "name": "Quilava",
        "pokedex_number": "156",
        "experience_growth": "1059860"
    },
    {
        "name": "Typhlosion",
        "pokedex_number": "157",
        "experience_growth": "1059860"
    },
    {
        "name": "Totodile",
        "pokedex_number": "158",
        "experience_growth": "1059860"
    },
    {
        "name": "Croconaw",
        "pokedex_number": "159",
        "experience_growth": "1059860"
    },
    {
        "name": "Feraligatr",
        "pokedex_number": "160",
        "experience_growth": "1059860"
    },
    {
        "name": "Sentret",
        "pokedex_number": "161",
        "experience_growth": "1000000"
    },
    {
        "name": "Furret",
        "pokedex_number": "162",
        "experience_growth": "1000000"
    },
    {
        "name": "Hoothoot",
        "pokedex_number": "163",
        "experience_growth": "1000000"
    },
    {
        "name": "Noctowl",
        "pokedex_number": "164",
        "experience_growth": "1000000"
    },
    {
        "name": "Ledyba",
        "pokedex_number": "165",
        "experience_growth": "800000"
    },
    {
        "name": "Ledian",
        "pokedex_number": "166",
        "experience_growth": "800000"
    },
    {
        "name": "Spinarak",
        "pokedex_number": "167",
        "experience_growth": "800000"
    },
    {
        "name": "Ariados",
        "pokedex_number": "168",
        "experience_growth": "800000"
    },
    {
        "name": "Crobat",
        "pokedex_number": "169",
        "experience_growth": "1000000"
    },
    {
        "name": "Chinchou",
        "pokedex_number": "170",
        "experience_growth": "1250000"
    },
    {
        "name": "Lanturn",
        "pokedex_number": "171",
        "experience_growth": "1250000"
    },
    {
        "name": "Pichu",
        "pokedex_number": "172",
        "experience_growth": "1000000"
    },
    {
        "name": "Cleffa",
        "pokedex_number": "173",
        "experience_growth": "800000"
    },
    {
        "name": "Igglybuff",
        "pokedex_number": "174",
        "experience_growth": "800000"
    },
    {
        "name": "Togepi",
        "pokedex_number": "175",
        "experience_growth": "800000"
    },
    {
        "name": "Togetic",
        "pokedex_number": "176",
        "experience_growth": "800000"
    },
    {
        "name": "Natu",
        "pokedex_number": "177",
        "experience_growth": "1000000"
    },
    {
        "name": "Xatu",
        "pokedex_number": "178",
        "experience_growth": "1000000"
    },
    {
        "name": "Mareep",
        "pokedex_number": "179",
        "experience_growth": "1059860"
    },
    {
        "name": "Flaaffy",
        "pokedex_number": "180",
        "experience_growth": "1059860"
    },
    {
        "name": "Ampharos",
        "pokedex_number": "181",
        "experience_growth": "1059860"
    },
    {
        "name": "Bellossom",
        "pokedex_number": "182",
        "experience_growth": "1059860"
    },
    {
        "name": "Marill",
        "pokedex_number": "183",
        "experience_growth": "800000"
    },
    {
        "name": "Azumarill",
        "pokedex_number": "184",
        "experience_growth": "800000"
    },
    {
        "name": "Sudowoodo",
        "pokedex_number": "185",
        "experience_growth": "1000000"
    },
    {
        "name": "Politoed",
        "pokedex_number": "186",
        "experience_growth": "1059860"
    },
    {
        "name": "Hoppip",
        "pokedex_number": "187",
        "experience_growth": "1059860"
    },
    {
        "name": "Skiploom",
        "pokedex_number": "188",
        "experience_growth": "1059860"
    },
    {
        "name": "Jumpluff",
        "pokedex_number": "189",
        "experience_growth": "1059860"
    },
    {
        "name": "Aipom",
        "pokedex_number": "190",
        "experience_growth": "800000"
    },
    {
        "name": "Sunkern",
        "pokedex_number": "191",
        "experience_growth": "1059860"
    },
    {
        "name": "Sunflora",
        "pokedex_number": "192",
        "experience_growth": "1059860"
    },
    {
        "name": "Yanma",
        "pokedex_number": "193",
        "experience_growth": "1000000"
    },
    {
        "name": "Wooper",
        "pokedex_number": "194",
        "experience_growth": "1000000"
    },
    {
        "name": "Quagsire",
        "pokedex_number": "195",
        "experience_growth": "1000000"
    },
    {
        "name": "Espeon",
        "pokedex_number": "196",
        "experience_growth": "1000000"
    },
    {
        "name": "Umbreon",
        "pokedex_number": "197",
        "experience_growth": "1000000"
    },
    {
        "name": "Murkrow",
        "pokedex_number": "198",
        "experience_growth": "1059860"
    },
    {
        "name": "Slowking",
        "pokedex_number": "199",
        "experience_growth": "1000000"
    },
    {
        "name": "Misdreavus",
        "pokedex_number": "200",
        "experience_growth": "800000"
    },
    {
        "name": "Unown",
        "pokedex_number": "201",
        "experience_growth": "1000000"
    },
    {
        "name": "Wobbuffet",
        "pokedex_number": "202",
        "experience_growth": "1000000"
    },
    {
        "name": "Girafarig",
        "pokedex_number": "203",
        "experience_growth": "1000000"
    },
    {
        "name": "Pineco",
        "pokedex_number": "204",
        "experience_growth": "1000000"
    },
    {
        "name": "Forretress",
        "pokedex_number": "205",
        "experience_growth": "1000000"
    },
    {
        "name": "Dunsparce",
        "pokedex_number": "206",
        "experience_growth": "1000000"
    },
    {
        "name": "Gligar",
        "pokedex_number": "207",
        "experience_growth": "1059860"
    },
    {
        "name": "Steelix",
        "pokedex_number": "208",
        "experience_growth": "1000000"
    },
    {
        "name": "Snubbull",
        "pokedex_number": "209",
        "experience_growth": "800000"
    },
    {
        "name": "Granbull",
        "pokedex_number": "210",
        "experience_growth": "800000"
    },
    {
        "name": "Qwilfish",
        "pokedex_number": "211",
        "experience_growth": "1000000"
    },
    {
        "name": "Scizor",
        "pokedex_number": "212",
        "experience_growth": "1000000"
    },
    {
        "name": "Shuckle",
        "pokedex_number": "213",
        "experience_growth": "1059860"
    },
    {
        "name": "Heracross",
        "pokedex_number": "214",
        "experience_growth": "1250000"
    },
    {
        "name": "Sneasel",
        "pokedex_number": "215",
        "experience_growth": "1059860"
    },
    {
        "name": "Teddiursa",
        "pokedex_number": "216",
        "experience_growth": "1000000"
    },
    {
        "name": "Ursaring",
        "pokedex_number": "217",
        "experience_growth": "1000000"
    },
    {
        "name": "Slugma",
        "pokedex_number": "218",
        "experience_growth": "1000000"
    },
    {
        "name": "Magcargo",
        "pokedex_number": "219",
        "experience_growth": "1000000"
    },
    {
        "name": "Swinub",
        "pokedex_number": "220",
        "experience_growth": "1250000"
    },
    {
        "name": "Piloswine",
        "pokedex_number": "221",
        "experience_growth": "1250000"
    },
    {
        "name": "Corsola",
        "pokedex_number": "222",
        "experience_growth": "800000"
    },
    {
        "name": "Remoraid",
        "pokedex_number": "223",
        "experience_growth": "1000000"
    },
    {
        "name": "Octillery",
        "pokedex_number": "224",
        "experience_growth": "1000000"
    },
    {
        "name": "Delibird",
        "pokedex_number": "225",
        "experience_growth": "800000"
    },
    {
        "name": "Mantine",
        "pokedex_number": "226",
        "experience_growth": "1250000"
    },
    {
        "name": "Skarmory",
        "pokedex_number": "227",
        "experience_growth": "1250000"
    },
    {
        "name": "Houndour",
        "pokedex_number": "228",
        "experience_growth": "1250000"
    },
    {
        "name": "Houndoom",
        "pokedex_number": "229",
        "experience_growth": "1250000"
    },
    {
        "name": "Kingdra",
        "pokedex_number": "230",
        "experience_growth": "1000000"
    },
    {
        "name": "Phanpy",
        "pokedex_number": "231",
        "experience_growth": "1000000"
    },
    {
        "name": "Donphan",
        "pokedex_number": "232",
        "experience_growth": "1000000"
    },
    {
        "name": "Porygon2",
        "pokedex_number": "233",
        "experience_growth": "1000000"
    },
    {
        "name": "Stantler",
        "pokedex_number": "234",
        "experience_growth": "1250000"
    },
    {
        "name": "Smeargle",
        "pokedex_number": "235",
        "experience_growth": "800000"
    },
    {
        "name": "Tyrogue",
        "pokedex_number": "236",
        "experience_growth": "1000000"
    },
    {
        "name": "Hitmontop",
        "pokedex_number": "237",
        "experience_growth": "1000000"
    },
    {
        "name": "Smoochum",
        "pokedex_number": "238",
        "experience_growth": "1000000"
    },
    {
        "name": "Elekid",
        "pokedex_number": "239",
        "experience_growth": "1000000"
    },
    {
        "name": "Magby",
        "pokedex_number": "240",
        "experience_growth": "1000000"
    },
    {
        "name": "Miltank",
        "pokedex_number": "241",
        "experience_growth": "1250000"
    },
    {
        "name": "Blissey",
        "pokedex_number": "242",
        "experience_growth": "800000"
    },
    {
        "name": "Raikou",
        "pokedex_number": "243",
        "experience_growth": "1250000"
    },
    {
        "name": "Entei",
        "pokedex_number": "244",
        "experience_growth": "1250000"
    },
    {
        "name": "Suicune",
        "pokedex_number": "245",
        "experience_growth": "1250000"
    },
    {
        "name": "Larvitar",
        "pokedex_number": "246",
        "experience_growth": "1250000"
    },
    {
        "name": "Pupitar",
        "pokedex_number": "247",
        "experience_growth": "1250000"
    },
    {
        "name": "Tyranitar",
        "pokedex_number": "248",
        "experience_growth": "1250000"
    },
    {
        "name": "Lugia",
        "pokedex_number": "249",
        "experience_growth": "1250000"
    },
    {
        "name": "Ho-Oh",
        "pokedex_number": "250",
        "experience_growth": "1250000"
    },
    {
        "name": "Celebi",
        "pokedex_number": "251",
        "experience_growth": "1059860"
    },
    {
        "name": "Treecko",
        "pokedex_number": "252",
        "experience_growth": "1059860"
    },
    {
        "name": "Grovyle",
        "pokedex_number": "253",
        "experience_growth": "1059860"
    },
    {
        "name": "Sceptile",
        "pokedex_number": "254",
        "experience_growth": "1059860"
    },
    {
        "name": "Torchic",
        "pokedex_number": "255",
        "experience_growth": "1059860"
    },
    {
        "name": "Combusken",
        "pokedex_number": "256",
        "experience_growth": "1059860"
    },
    {
        "name": "Blaziken",
        "pokedex_number": "257",
        "experience_growth": "1059860"
    },
    {
        "name": "Mudkip",
        "pokedex_number": "258",
        "experience_growth": "1059860"
    },
    {
        "name": "Marshtomp",
        "pokedex_number": "259",
        "experience_growth": "1059860"
    },
    {
        "name": "Swampert",
        "pokedex_number": "260",
        "experience_growth": "1059860"
    },
    {
        "name": "Poochyena",
        "pokedex_number": "261",
        "experience_growth": "1000000"
    },
    {
        "name": "Mightyena",
        "pokedex_number": "262",
        "experience_growth": "1000000"
    },
    {
        "name": "Zigzagoon",
        "pokedex_number": "263",
        "experience_growth": "1000000"
    },
    {
        "name": "Linoone",
        "pokedex_number": "264",
        "experience_growth": "1000000"
    },
    {
        "name": "Wurmple",
        "pokedex_number": "265",
        "experience_growth": "1000000"
    },
    {
        "name": "Silcoon",
        "pokedex_number": "266",
        "experience_growth": "1000000"
    },
    {
        "name": "Beautifly",
        "pokedex_number": "267",
        "experience_growth": "1000000"
    },
    {
        "name": "Cascoon",
        "pokedex_number": "268",
        "experience_growth": "1000000"
    },
    {
        "name": "Dustox",
        "pokedex_number": "269",
        "experience_growth": "1000000"
    },
    {
        "name": "Lotad",
        "pokedex_number": "270",
        "experience_growth": "1059860"
    },
    {
        "name": "Lombre",
        "pokedex_number": "271",
        "experience_growth": "1059860"
    },
    {
        "name": "Ludicolo",
        "pokedex_number": "272",
        "experience_growth": "1059860"
    },
    {
        "name": "Seedot",
        "pokedex_number": "273",
        "experience_growth": "1059860"
    },
    {
        "name": "Nuzleaf",
        "pokedex_number": "274",
        "experience_growth": "1059860"
    },
    {
        "name": "Shiftry",
        "pokedex_number": "275",
        "experience_growth": "1059860"
    },
    {
        "name": "Taillow",
        "pokedex_number": "276",
        "experience_growth": "1059860"
    },
    {
        "name": "Swellow",
        "pokedex_number": "277",
        "experience_growth": "1059860"
    },
    {
        "name": "Wingull",
        "pokedex_number": "278",
        "experience_growth": "1000000"
    },
    {
        "name": "Pelipper",
        "pokedex_number": "279",
        "experience_growth": "1000000"
    },
    {
        "name": "Ralts",
        "pokedex_number": "280",
        "experience_growth": "1250000"
    },
    {
        "name": "Kirlia",
        "pokedex_number": "281",
        "experience_growth": "1250000"
    },
    {
        "name": "Gardevoir",
        "pokedex_number": "282",
        "experience_growth": "1250000"
    },
    {
        "name": "Surskit",
        "pokedex_number": "283",
        "experience_growth": "1000000"
    },
    {
        "name": "Masquerain",
        "pokedex_number": "284",
        "experience_growth": "1000000"
    },
    {
        "name": "Shroomish",
        "pokedex_number": "285",
        "experience_growth": "1640000"
    },
    {
        "name": "Breloom",
        "pokedex_number": "286",
        "experience_growth": "1640000"
    },
    {
        "name": "Slakoth",
        "pokedex_number": "287",
        "experience_growth": "1250000"
    },
    {
        "name": "Vigoroth",
        "pokedex_number": "288",
        "experience_growth": "1250000"
    },
    {
        "name": "Slaking",
        "pokedex_number": "289",
        "experience_growth": "1250000"
    },
    {
        "name": "Nincada",
        "pokedex_number": "290",
        "experience_growth": "600000"
    },
    {
        "name": "Ninjask",
        "pokedex_number": "291",
        "experience_growth": "600000"
    },
    {
        "name": "Shedinja",
        "pokedex_number": "292",
        "experience_growth": "600000"
    },
    {
        "name": "Whismur",
        "pokedex_number": "293",
        "experience_growth": "1059860"
    },
    {
        "name": "Loudred",
        "pokedex_number": "294",
        "experience_growth": "1059860"
    },
    {
        "name": "Exploud",
        "pokedex_number": "295",
        "experience_growth": "1059860"
    },
    {
        "name": "Makuhita",
        "pokedex_number": "296",
        "experience_growth": "1640000"
    },
    {
        "name": "Hariyama",
        "pokedex_number": "297",
        "experience_growth": "1640000"
    },
    {
        "name": "Azurill",
        "pokedex_number": "298",
        "experience_growth": "800000"
    },
    {
        "name": "Nosepass",
        "pokedex_number": "299",
        "experience_growth": "1000000"
    },
    {
        "name": "Skitty",
        "pokedex_number": "300",
        "experience_growth": "800000"
    },
    {
        "name": "Delcatty",
        "pokedex_number": "301",
        "experience_growth": "800000"
    },
    {
        "name": "Sableye",
        "pokedex_number": "302",
        "experience_growth": "1059860"
    },
    {
        "name": "Mawile",
        "pokedex_number": "303",
        "experience_growth": "800000"
    },
    {
        "name": "Aron",
        "pokedex_number": "304",
        "experience_growth": "1250000"
    },
    {
        "name": "Lairon",
        "pokedex_number": "305",
        "experience_growth": "1250000"
    },
    {
        "name": "Aggron",
        "pokedex_number": "306",
        "experience_growth": "1250000"
    },
    {
        "name": "Meditite",
        "pokedex_number": "307",
        "experience_growth": "1000000"
    },
    {
        "name": "Medicham",
        "pokedex_number": "308",
        "experience_growth": "1000000"
    },
    {
        "name": "Electrike",
        "pokedex_number": "309",
        "experience_growth": "1250000"
    },
    {
        "name": "Manectric",
        "pokedex_number": "310",
        "experience_growth": "1250000"
    },
    {
        "name": "Plusle",
        "pokedex_number": "311",
        "experience_growth": "1000000"
    },
    {
        "name": "Minun",
        "pokedex_number": "312",
        "experience_growth": "1000000"
    },
    {
        "name": "Volbeat",
        "pokedex_number": "313",
        "experience_growth": "600000"
    },
    {
        "name": "Illumise",
        "pokedex_number": "314",
        "experience_growth": "1640000"
    },
    {
        "name": "Roselia",
        "pokedex_number": "315",
        "experience_growth": "1059860"
    },
    {
        "name": "Gulpin",
        "pokedex_number": "316",
        "experience_growth": "1640000"
    },
    {
        "name": "Swalot",
        "pokedex_number": "317",
        "experience_growth": "1640000"
    },
    {
        "name": "Carvanha",
        "pokedex_number": "318",
        "experience_growth": "1250000"
    },
    {
        "name": "Sharpedo",
        "pokedex_number": "319",
        "experience_growth": "1250000"
    },
    {
        "name": "Wailmer",
        "pokedex_number": "320",
        "experience_growth": "1640000"
    },
    {
        "name": "Wailord",
        "pokedex_number": "321",
        "experience_growth": "1640000"
    },
    {
        "name": "Numel",
        "pokedex_number": "322",
        "experience_growth": "1000000"
    },
    {
        "name": "Camerupt",
        "pokedex_number": "323",
        "experience_growth": "1000000"
    },
    {
        "name": "Torkoal",
        "pokedex_number": "324",
        "experience_growth": "1000000"
    },
    {
        "name": "Spoink",
        "pokedex_number": "325",
        "experience_growth": "800000"
    },
    {
        "name": "Grumpig",
        "pokedex_number": "326",
        "experience_growth": "800000"
    },
    {
        "name": "Spinda",
        "pokedex_number": "327",
        "experience_growth": "800000"
    },
    {
        "name": "Trapinch",
        "pokedex_number": "328",
        "experience_growth": "1059860"
    },
    {
        "name": "Vibrava",
        "pokedex_number": "329",
        "experience_growth": "1059860"
    },
    {
        "name": "Flygon",
        "pokedex_number": "330",
        "experience_growth": "1059860"
    },
    {
        "name": "Cacnea",
        "pokedex_number": "331",
        "experience_growth": "1059860"
    },
    {
        "name": "Cacturne",
        "pokedex_number": "332",
        "experience_growth": "1059860"
    },
    {
        "name": "Swablu",
        "pokedex_number": "333",
        "experience_growth": "600000"
    },
    {
        "name": "Altaria",
        "pokedex_number": "334",
        "experience_growth": "600000"
    },
    {
        "name": "Zangoose",
        "pokedex_number": "335",
        "experience_growth": "600000"
    },
    {
        "name": "Seviper",
        "pokedex_number": "336",
        "experience_growth": "1640000"
    },
    {
        "name": "Lunatone",
        "pokedex_number": "337",
        "experience_growth": "800000"
    },
    {
        "name": "Solrock",
        "pokedex_number": "338",
        "experience_growth": "800000"
    },
    {
        "name": "Barboach",
        "pokedex_number": "339",
        "experience_growth": "1000000"
    },
    {
        "name": "Whiscash",
        "pokedex_number": "340",
        "experience_growth": "1000000"
    },
    {
        "name": "Corphish",
        "pokedex_number": "341",
        "experience_growth": "1640000"
    },
    {
        "name": "Crawdaunt",
        "pokedex_number": "342",
        "experience_growth": "1640000"
    },
    {
        "name": "Baltoy",
        "pokedex_number": "343",
        "experience_growth": "1000000"
    },
    {
        "name": "Claydol",
        "pokedex_number": "344",
        "experience_growth": "1000000"
    },
    {
        "name": "Lileep",
        "pokedex_number": "345",
        "experience_growth": "600000"
    },
    {
        "name": "Cradily",
        "pokedex_number": "346",
        "experience_growth": "600000"
    },
    {
        "name": "Anorith",
        "pokedex_number": "347",
        "experience_growth": "600000"
    },
    {
        "name": "Armaldo",
        "pokedex_number": "348",
        "experience_growth": "600000"
    },
    {
        "name": "Feebas",
        "pokedex_number": "349",
        "experience_growth": "600000"
    },
    {
        "name": "Milotic",
        "pokedex_number": "350",
        "experience_growth": "600000"
    },
    {
        "name": "Castform",
        "pokedex_number": "351",
        "experience_growth": "1000000"
    },
    {
        "name": "Kecleon",
        "pokedex_number": "352",
        "experience_growth": "1059860"
    },
    {
        "name": "Shuppet",
        "pokedex_number": "353",
        "experience_growth": "800000"
    },
    {
        "name": "Banette",
        "pokedex_number": "354",
        "experience_growth": "800000"
    },
    {
        "name": "Duskull",
        "pokedex_number": "355",
        "experience_growth": "800000"
    },
    {
        "name": "Dusclops",
        "pokedex_number": "356",
        "experience_growth": "800000"
    },
    {
        "name": "Tropius",
        "pokedex_number": "357",
        "experience_growth": "1250000"
    },
    {
        "name": "Chimecho",
        "pokedex_number": "358",
        "experience_growth": "800000"
    },
    {
        "name": "Absol",
        "pokedex_number": "359",
        "experience_growth": "1059860"
    },
    {
        "name": "Wynaut",
        "pokedex_number": "360",
        "experience_growth": "1000000"
    },
    {
        "name": "Snorunt",
        "pokedex_number": "361",
        "experience_growth": "1000000"
    },
    {
        "name": "Glalie",
        "pokedex_number": "362",
        "experience_growth": "1000000"
    },
    {
        "name": "Spheal",
        "pokedex_number": "363",
        "experience_growth": "1059860"
    },
    {
        "name": "Sealeo",
        "pokedex_number": "364",
        "experience_growth": "1059860"
    },
    {
        "name": "Walrein",
        "pokedex_number": "365",
        "experience_growth": "1059860"
    },
    {
        "name": "Clamperl",
        "pokedex_number": "366",
        "experience_growth": "600000"
    },
    {
        "name": "Huntail",
        "pokedex_number": "367",
        "experience_growth": "600000"
    },
    {
        "name": "Gorebyss",
        "pokedex_number": "368",
        "experience_growth": "600000"
    },
    {
        "name": "Relicanth",
        "pokedex_number": "369",
        "experience_growth": "1250000"
    },
    {
        "name": "Luvdisc",
        "pokedex_number": "370",
        "experience_growth": "800000"
    },
    {
        "name": "Bagon",
        "pokedex_number": "371",
        "experience_growth": "1250000"
    },
    {
        "name": "Shelgon",
        "pokedex_number": "372",
        "experience_growth": "1250000"
    },
    {
        "name": "Salamence",
        "pokedex_number": "373",
        "experience_growth": "1250000"
    },
    {
        "name": "Beldum",
        "pokedex_number": "374",
        "experience_growth": "1250000"
    },
    {
        "name": "Metang",
        "pokedex_number": "375",
        "experience_growth": "1250000"
    },
    {
        "name": "Metagross",
        "pokedex_number": "376",
        "experience_growth": "1250000"
    },
    {
        "name": "Regirock",
        "pokedex_number": "377",
        "experience_growth": "1250000"
    },
    {
        "name": "Regice",
        "pokedex_number": "378",
        "experience_growth": "1250000"
    },
    {
        "name": "Registeel",
        "pokedex_number": "379",
        "experience_growth": "1250000"
    },
    {
        "name": "Latias",
        "pokedex_number": "380",
        "experience_growth": "1250000"
    },
    {
        "name": "Latios",
        "pokedex_number": "381",
        "experience_growth": "1250000"
    },
    {
        "name": "Kyogre",
        "pokedex_number": "382",
        "experience_growth": "1250000"
    },
    {
        "name": "Groudon",
        "pokedex_number": "383",
        "experience_growth": "1250000"
    },
    {
        "name": "Rayquaza",
        "pokedex_number": "384",
        "experience_growth": "1250000"
    },
    {
        "name": "Jirachi",
        "pokedex_number": "385",
        "experience_growth": "1250000"
    },
    {
        "name": "Deoxys",
        "pokedex_number": "386",
        "experience_growth": "1250000"
    },
    {
        "name": "Turtwig",
        "pokedex_number": "387",
        "experience_growth": "1059860"
    },
    {
        "name": "Grotle",
        "pokedex_number": "388",
        "experience_growth": "1059860"
    },
    {
        "name": "Torterra",
        "pokedex_number": "389",
        "experience_growth": "1059860"
    },
    {
        "name": "Chimchar",
        "pokedex_number": "390",
        "experience_growth": "1059860"
    },
    {
        "name": "Monferno",
        "pokedex_number": "391",
        "experience_growth": "1059860"
    },
    {
        "name": "Infernape",
        "pokedex_number": "392",
        "experience_growth": "1059860"
    },
    {
        "name": "Piplup",
        "pokedex_number": "393",
        "experience_growth": "1059860"
    },
    {
        "name": "Prinplup",
        "pokedex_number": "394",
        "experience_growth": "1059860"
    },
    {
        "name": "Empoleon",
        "pokedex_number": "395",
        "experience_growth": "1059860"
    },
    {
        "name": "Starly",
        "pokedex_number": "396",
        "experience_growth": "1059860"
    },
    {
        "name": "Staravia",
        "pokedex_number": "397",
        "experience_growth": "1059860"
    },
    {
        "name": "Staraptor",
        "pokedex_number": "398",
        "experience_growth": "1059860"
    },
    {
        "name": "Bidoof",
        "pokedex_number": "399",
        "experience_growth": "1000000"
    },
    {
        "name": "Bibarel",
        "pokedex_number": "400",
        "experience_growth": "1000000"
    },
    {
        "name": "Kricketot",
        "pokedex_number": "401",
        "experience_growth": "1059860"
    },
    {
        "name": "Kricketune",
        "pokedex_number": "402",
        "experience_growth": "1059860"
    },
    {
        "name": "Shinx",
        "pokedex_number": "403",
        "experience_growth": "1059860"
    },
    {
        "name": "Luxio",
        "pokedex_number": "404",
        "experience_growth": "1059860"
    },
    {
        "name": "Luxray",
        "pokedex_number": "405",
        "experience_growth": "1059860"
    },
    {
        "name": "Budew",
        "pokedex_number": "406",
        "experience_growth": "1059860"
    },
    {
        "name": "Roserade",
        "pokedex_number": "407",
        "experience_growth": "1059860"
    },
    {
        "name": "Cranidos",
        "pokedex_number": "408",
        "experience_growth": "600000"
    },
    {
        "name": "Rampardos",
        "pokedex_number": "409",
        "experience_growth": "600000"
    },
    {
        "name": "Shieldon",
        "pokedex_number": "410",
        "experience_growth": "600000"
    },
    {
        "name": "Bastiodon",
        "pokedex_number": "411",
        "experience_growth": "600000"
    },
    {
        "name": "Burmy",
        "pokedex_number": "412",
        "experience_growth": "1000000"
    },
    {
        "name": "Wormadam",
        "pokedex_number": "413",
        "experience_growth": "1000000"
    },
    {
        "name": "Mothim",
        "pokedex_number": "414",
        "experience_growth": "1000000"
    },
    {
        "name": "Combee",
        "pokedex_number": "415",
        "experience_growth": "1059860"
    },
    {
        "name": "Vespiquen",
        "pokedex_number": "416",
        "experience_growth": "1059860"
    },
    {
        "name": "Pachirisu",
        "pokedex_number": "417",
        "experience_growth": "1000000"
    },
    {
        "name": "Buizel",
        "pokedex_number": "418",
        "experience_growth": "1000000"
    },
    {
        "name": "Floatzel",
        "pokedex_number": "419",
        "experience_growth": "1000000"
    },
    {
        "name": "Cherubi",
        "pokedex_number": "420",
        "experience_growth": "1000000"
    },
    {
        "name": "Cherrim",
        "pokedex_number": "421",
        "experience_growth": "1000000"
    },
    {
        "name": "Shellos",
        "pokedex_number": "422",
        "experience_growth": "1000000"
    },
    {
        "name": "Gastrodon",
        "pokedex_number": "423",
        "experience_growth": "1000000"
    },
    {
        "name": "Ambipom",
        "pokedex_number": "424",
        "experience_growth": "800000"
    },
    {
        "name": "Drifloon",
        "pokedex_number": "425",
        "experience_growth": "1640000"
    },
    {
        "name": "Drifblim",
        "pokedex_number": "426",
        "experience_growth": "1640000"
    },
    {
        "name": "Buneary",
        "pokedex_number": "427",
        "experience_growth": "1000000"
    },
    {
        "name": "Lopunny",
        "pokedex_number": "428",
        "experience_growth": "1000000"
    },
    {
        "name": "Mismagius",
        "pokedex_number": "429",
        "experience_growth": "800000"
    },
    {
        "name": "Honchkrow",
        "pokedex_number": "430",
        "experience_growth": "1059860"
    },
    {
        "name": "Glameow",
        "pokedex_number": "431",
        "experience_growth": "800000"
    },
    {
        "name": "Purugly",
        "pokedex_number": "432",
        "experience_growth": "800000"
    },
    {
        "name": "Chingling",
        "pokedex_number": "433",
        "experience_growth": "800000"
    },
    {
        "name": "Stunky",
        "pokedex_number": "434",
        "experience_growth": "1000000"
    },
    {
        "name": "Skuntank",
        "pokedex_number": "435",
        "experience_growth": "1000000"
    },
    {
        "name": "Bronzor",
        "pokedex_number": "436",
        "experience_growth": "1000000"
    },
    {
        "name": "Bronzong",
        "pokedex_number": "437",
        "experience_growth": "1000000"
    },
    {
        "name": "Bonsly",
        "pokedex_number": "438",
        "experience_growth": "1000000"
    },
    {
        "name": "Mime Jr.",
        "pokedex_number": "439",
        "experience_growth": "1000000"
    },
    {
        "name": "Happiny",
        "pokedex_number": "440",
        "experience_growth": "800000"
    },
    {
        "name": "Chatot",
        "pokedex_number": "441",
        "experience_growth": "1059860"
    },
    {
        "name": "Spiritomb",
        "pokedex_number": "442",
        "experience_growth": "1000000"
    },
    {
        "name": "Gible",
        "pokedex_number": "443",
        "experience_growth": "1250000"
    },
    {
        "name": "Gabite",
        "pokedex_number": "444",
        "experience_growth": "1250000"
    },
    {
        "name": "Garchomp",
        "pokedex_number": "445",
        "experience_growth": "1250000"
    },
    {
        "name": "Munchlax",
        "pokedex_number": "446",
        "experience_growth": "1250000"
    },
    {
        "name": "Riolu",
        "pokedex_number": "447",
        "experience_growth": "1059860"
    },
    {
        "name": "Lucario",
        "pokedex_number": "448",
        "experience_growth": "1059860"
    },
    {
        "name": "Hippopotas",
        "pokedex_number": "449",
        "experience_growth": "1250000"
    },
    {
        "name": "Hippowdon",
        "pokedex_number": "450",
        "experience_growth": "1250000"
    },
    {
        "name": "Skorupi",
        "pokedex_number": "451",
        "experience_growth": "1250000"
    },
    {
        "name": "Drapion",
        "pokedex_number": "452",
        "experience_growth": "1250000"
    },
    {
        "name": "Croagunk",
        "pokedex_number": "453",
        "experience_growth": "1000000"
    },
    {
        "name": "Toxicroak",
        "pokedex_number": "454",
        "experience_growth": "1000000"
    },
    {
        "name": "Carnivine",
        "pokedex_number": "455",
        "experience_growth": "1250000"
    },
    {
        "name": "Finneon",
        "pokedex_number": "456",
        "experience_growth": "600000"
    },
    {
        "name": "Lumineon",
        "pokedex_number": "457",
        "experience_growth": "600000"
    },
    {
        "name": "Mantyke",
        "pokedex_number": "458",
        "experience_growth": "1250000"
    },
    {
        "name": "Snover",
        "pokedex_number": "459",
        "experience_growth": "1250000"
    },
    {
        "name": "Abomasnow",
        "pokedex_number": "460",
        "experience_growth": "1250000"
    },
    {
        "name": "Weavile",
        "pokedex_number": "461",
        "experience_growth": "1059860"
    },
    {
        "name": "Magnezone",
        "pokedex_number": "462",
        "experience_growth": "1000000"
    },
    {
        "name": "Lickilicky",
        "pokedex_number": "463",
        "experience_growth": "1000000"
    },
    {
        "name": "Rhyperior",
        "pokedex_number": "464",
        "experience_growth": "1250000"
    },
    {
        "name": "Tangrowth",
        "pokedex_number": "465",
        "experience_growth": "1000000"
    },
    {
        "name": "Electivire",
        "pokedex_number": "466",
        "experience_growth": "1000000"
    },
    {
        "name": "Magmortar",
        "pokedex_number": "467",
        "experience_growth": "1000000"
    },
    {
        "name": "Togekiss",
        "pokedex_number": "468",
        "experience_growth": "800000"
    },
    {
        "name": "Yanmega",
        "pokedex_number": "469",
        "experience_growth": "1000000"
    },
    {
        "name": "Leafeon",
        "pokedex_number": "470",
        "experience_growth": "1000000"
    },
    {
        "name": "Glaceon",
        "pokedex_number": "471",
        "experience_growth": "1000000"
    },
    {
        "name": "Gliscor",
        "pokedex_number": "472",
        "experience_growth": "1059860"
    },
    {
        "name": "Mamoswine",
        "pokedex_number": "473",
        "experience_growth": "1250000"
    },
    {
        "name": "Porygon-Z",
        "pokedex_number": "474",
        "experience_growth": "1000000"
    },
    {
        "name": "Gallade",
        "pokedex_number": "475",
        "experience_growth": "1250000"
    },
    {
        "name": "Probopass",
        "pokedex_number": "476",
        "experience_growth": "1000000"
    },
    {
        "name": "Dusknoir",
        "pokedex_number": "477",
        "experience_growth": "800000"
    },
    {
        "name": "Froslass",
        "pokedex_number": "478",
        "experience_growth": "1000000"
    },
    {
        "name": "Rotom",
        "pokedex_number": "479",
        "experience_growth": "1000000"
    },
    {
        "name": "Uxie",
        "pokedex_number": "480",
        "experience_growth": "1250000"
    },
    {
        "name": "Mesprit",
        "pokedex_number": "481",
        "experience_growth": "1250000"
    },
    {
        "name": "Azelf",
        "pokedex_number": "482",
        "experience_growth": "1250000"
    },
    {
        "name": "Dialga",
        "pokedex_number": "483",
        "experience_growth": "1250000"
    },
    {
        "name": "Palkia",
        "pokedex_number": "484",
        "experience_growth": "1250000"
    },
    {
        "name": "Heatran",
        "pokedex_number": "485",
        "experience_growth": "1250000"
    },
    {
        "name": "Regigigas",
        "pokedex_number": "486",
        "experience_growth": "1250000"
    },
    {
        "name": "Giratina",
        "pokedex_number": "487",
        "experience_growth": "1250000"
    },
    {
        "name": "Cresselia",
        "pokedex_number": "488",
        "experience_growth": "1250000"
    },
    {
        "name": "Phione",
        "pokedex_number": "489",
        "experience_growth": "1250000"
    },
    {
        "name": "Manaphy",
        "pokedex_number": "490",
        "experience_growth": "1250000"
    },
    {
        "name": "Darkrai",
        "pokedex_number": "491",
        "experience_growth": "1250000"
    },
    {
        "name": "Shaymin",
        "pokedex_number": "492",
        "experience_growth": "1059860"
    },
    {
        "name": "Arceus",
        "pokedex_number": "493",
        "experience_growth": "1250000"
    },
    {
        "name": "Victini",
        "pokedex_number": "494",
        "experience_growth": "1250000"
    },
    {
        "name": "Snivy",
        "pokedex_number": "495",
        "experience_growth": "1059860"
    },
    {
        "name": "Servine",
        "pokedex_number": "496",
        "experience_growth": "1059860"
    },
    {
        "name": "Serperior",
        "pokedex_number": "497",
        "experience_growth": "1059860"
    },
    {
        "name": "Tepig",
        "pokedex_number": "498",
        "experience_growth": "1059860"
    },
    {
        "name": "Pignite",
        "pokedex_number": "499",
        "experience_growth": "1059860"
    },
    {
        "name": "Emboar",
        "pokedex_number": "500",
        "experience_growth": "1059860"
    },
    {
        "name": "Oshawott",
        "pokedex_number": "501",
        "experience_growth": "1059860"
    },
    {
        "name": "Dewott",
        "pokedex_number": "502",
        "experience_growth": "1059860"
    },
    {
        "name": "Samurott",
        "pokedex_number": "503",
        "experience_growth": "1059860"
    },
    {
        "name": "Patrat",
        "pokedex_number": "504",
        "experience_growth": "1000000"
    },
    {
        "name": "Watchog",
        "pokedex_number": "505",
        "experience_growth": "1000000"
    },
    {
        "name": "Lillipup",
        "pokedex_number": "506",
        "experience_growth": "1059860"
    },
    {
        "name": "Herdier",
        "pokedex_number": "507",
        "experience_growth": "1059860"
    },
    {
        "name": "Stoutland",
        "pokedex_number": "508",
        "experience_growth": "1059860"
    },
    {
        "name": "Purrloin",
        "pokedex_number": "509",
        "experience_growth": "1000000"
    },
    {
        "name": "Liepard",
        "pokedex_number": "510",
        "experience_growth": "1000000"
    },
    {
        "name": "Pansage",
        "pokedex_number": "511",
        "experience_growth": "1000000"
    },
    {
        "name": "Simisage",
        "pokedex_number": "512",
        "experience_growth": "1000000"
    },
    {
        "name": "Pansear",
        "pokedex_number": "513",
        "experience_growth": "1000000"
    },
    {
        "name": "Simisear",
        "pokedex_number": "514",
        "experience_growth": "1000000"
    },
    {
        "name": "Panpour",
        "pokedex_number": "515",
        "experience_growth": "1000000"
    },
    {
        "name": "Simipour",
        "pokedex_number": "516",
        "experience_growth": "1000000"
    },
    {
        "name": "Munna",
        "pokedex_number": "517",
        "experience_growth": "800000"
    },
    {
        "name": "Musharna",
        "pokedex_number": "518",
        "experience_growth": "800000"
    },
    {
        "name": "Pidove",
        "pokedex_number": "519",
        "experience_growth": "1059860"
    },
    {
        "name": "Tranquill",
        "pokedex_number": "520",
        "experience_growth": "1059860"
    },
    {
        "name": "Unfezant",
        "pokedex_number": "521",
        "experience_growth": "1059860"
    },
    {
        "name": "Blitzle",
        "pokedex_number": "522",
        "experience_growth": "1000000"
    },
    {
        "name": "Zebstrika",
        "pokedex_number": "523",
        "experience_growth": "1000000"
    },
    {
        "name": "Roggenrola",
        "pokedex_number": "524",
        "experience_growth": "1059860"
    },
    {
        "name": "Boldore",
        "pokedex_number": "525",
        "experience_growth": "1059860"
    },
    {
        "name": "Gigalith",
        "pokedex_number": "526",
        "experience_growth": "1059860"
    },
    {
        "name": "Woobat",
        "pokedex_number": "527",
        "experience_growth": "1000000"
    },
    {
        "name": "Swoobat",
        "pokedex_number": "528",
        "experience_growth": "1000000"
    },
    {
        "name": "Drilbur",
        "pokedex_number": "529",
        "experience_growth": "1000000"
    },
    {
        "name": "Excadrill",
        "pokedex_number": "530",
        "experience_growth": "1000000"
    },
    {
        "name": "Audino",
        "pokedex_number": "531",
        "experience_growth": "800000"
    },
    {
        "name": "Timburr",
        "pokedex_number": "532",
        "experience_growth": "1059860"
    },
    {
        "name": "Gurdurr",
        "pokedex_number": "533",
        "experience_growth": "1059860"
    },
    {
        "name": "Conkeldurr",
        "pokedex_number": "534",
        "experience_growth": "1059860"
    },
    {
        "name": "Tympole",
        "pokedex_number": "535",
        "experience_growth": "1059860"
    },
    {
        "name": "Palpitoad",
        "pokedex_number": "536",
        "experience_growth": "1059860"
    },
    {
        "name": "Seismitoad",
        "pokedex_number": "537",
        "experience_growth": "1059860"
    },
    {
        "name": "Throh",
        "pokedex_number": "538",
        "experience_growth": "1000000"
    },
    {
        "name": "Sawk",
        "pokedex_number": "539",
        "experience_growth": "1000000"
    },
    {
        "name": "Sewaddle",
        "pokedex_number": "540",
        "experience_growth": "1059860"
    },
    {
        "name": "Swadloon",
        "pokedex_number": "541",
        "experience_growth": "1059860"
    },
    {
        "name": "Leavanny",
        "pokedex_number": "542",
        "experience_growth": "1059860"
    },
    {
        "name": "Venipede",
        "pokedex_number": "543",
        "experience_growth": "1059860"
    },
    {
        "name": "Whirlipede",
        "pokedex_number": "544",
        "experience_growth": "1059860"
    },
    {
        "name": "Scolipede",
        "pokedex_number": "545",
        "experience_growth": "1059860"
    },
    {
        "name": "Cottonee",
        "pokedex_number": "546",
        "experience_growth": "1000000"
    },
    {
        "name": "Whimsicott",
        "pokedex_number": "547",
        "experience_growth": "1000000"
    },
    {
        "name": "Petilil",
        "pokedex_number": "548",
        "experience_growth": "1000000"
    },
    {
        "name": "Lilligant",
        "pokedex_number": "549",
        "experience_growth": "1000000"
    },
    {
        "name": "Basculin",
        "pokedex_number": "550",
        "experience_growth": "1000000"
    },
    {
        "name": "Sandile",
        "pokedex_number": "551",
        "experience_growth": "1059860"
    },
    {
        "name": "Krokorok",
        "pokedex_number": "552",
        "experience_growth": "1059860"
    },
    {
        "name": "Krookodile",
        "pokedex_number": "553",
        "experience_growth": "1059860"
    },
    {
        "name": "Darumaka",
        "pokedex_number": "554",
        "experience_growth": "1059860"
    },
    {
        "name": "Darmanitan",
        "pokedex_number": "555",
        "experience_growth": "1059860"
    },
    {
        "name": "Maractus",
        "pokedex_number": "556",
        "experience_growth": "1000000"
    },
    {
        "name": "Dwebble",
        "pokedex_number": "557",
        "experience_growth": "1000000"
    },
    {
        "name": "Crustle",
        "pokedex_number": "558",
        "experience_growth": "1000000"
    },
    {
        "name": "Scraggy",
        "pokedex_number": "559",
        "experience_growth": "1000000"
    },
    {
        "name": "Scrafty",
        "pokedex_number": "560",
        "experience_growth": "1000000"
    },
    {
        "name": "Sigilyph",
        "pokedex_number": "561",
        "experience_growth": "1000000"
    },
    {
        "name": "Yamask",
        "pokedex_number": "562",
        "experience_growth": "1000000"
    },
    {
        "name": "Cofagrigus",
        "pokedex_number": "563",
        "experience_growth": "1000000"
    },
    {
        "name": "Tirtouga",
        "pokedex_number": "564",
        "experience_growth": "1000000"
    },
    {
        "name": "Carracosta",
        "pokedex_number": "565",
        "experience_growth": "1000000"
    },
    {
        "name": "Archen",
        "pokedex_number": "566",
        "experience_growth": "1000000"
    },
    {
        "name": "Archeops",
        "pokedex_number": "567",
        "experience_growth": "1000000"
    },
    {
        "name": "Trubbish",
        "pokedex_number": "568",
        "experience_growth": "1000000"
    },
    {
        "name": "Garbodor",
        "pokedex_number": "569",
        "experience_growth": "1000000"
    },
    {
        "name": "Zorua",
        "pokedex_number": "570",
        "experience_growth": "1059860"
    },
    {
        "name": "Zoroark",
        "pokedex_number": "571",
        "experience_growth": "1059860"
    },
    {
        "name": "Minccino",
        "pokedex_number": "572",
        "experience_growth": "800000"
    },
    {
        "name": "Cinccino",
        "pokedex_number": "573",
        "experience_growth": "800000"
    },
    {
        "name": "Gothita",
        "pokedex_number": "574",
        "experience_growth": "1059860"
    },
    {
        "name": "Gothorita",
        "pokedex_number": "575",
        "experience_growth": "1059860"
    },
    {
        "name": "Gothitelle",
        "pokedex_number": "576",
        "experience_growth": "1059860"
    },
    {
        "name": "Solosis",
        "pokedex_number": "577",
        "experience_growth": "1059860"
    },
    {
        "name": "Duosion",
        "pokedex_number": "578",
        "experience_growth": "1059860"
    },
    {
        "name": "Reuniclus",
        "pokedex_number": "579",
        "experience_growth": "1059860"
    },
    {
        "name": "Ducklett",
        "pokedex_number": "580",
        "experience_growth": "1000000"
    },
    {
        "name": "Swanna",
        "pokedex_number": "581",
        "experience_growth": "1000000"
    },
    {
        "name": "Vanillite",
        "pokedex_number": "582",
        "experience_growth": "1250000"
    },
    {
        "name": "Vanillish",
        "pokedex_number": "583",
        "experience_growth": "1250000"
    },
    {
        "name": "Vanilluxe",
        "pokedex_number": "584",
        "experience_growth": "1250000"
    },
    {
        "name": "Deerling",
        "pokedex_number": "585",
        "experience_growth": "1000000"
    },
    {
        "name": "Sawsbuck",
        "pokedex_number": "586",
        "experience_growth": "1000000"
    },
    {
        "name": "Emolga",
        "pokedex_number": "587",
        "experience_growth": "1000000"
    },
    {
        "name": "Karrablast",
        "pokedex_number": "588",
        "experience_growth": "1000000"
    },
    {
        "name": "Escavalier",
        "pokedex_number": "589",
        "experience_growth": "1000000"
    },
    {
        "name": "Foongus",
        "pokedex_number": "590",
        "experience_growth": "1000000"
    },
    {
        "name": "Amoonguss",
        "pokedex_number": "591",
        "experience_growth": "1000000"
    },
    {
        "name": "Frillish",
        "pokedex_number": "592",
        "experience_growth": "1000000"
    },
    {
        "name": "Jellicent",
        "pokedex_number": "593",
        "experience_growth": "1000000"
    },
    {
        "name": "Alomomola",
        "pokedex_number": "594",
        "experience_growth": "800000"
    },
    {
        "name": "Joltik",
        "pokedex_number": "595",
        "experience_growth": "1000000"
    },
    {
        "name": "Galvantula",
        "pokedex_number": "596",
        "experience_growth": "1000000"
    },
    {
        "name": "Ferroseed",
        "pokedex_number": "597",
        "experience_growth": "1000000"
    },
    {
        "name": "Ferrothorn",
        "pokedex_number": "598",
        "experience_growth": "1000000"
    },
    {
        "name": "Klink",
        "pokedex_number": "599",
        "experience_growth": "1059860"
    },
    {
        "name": "Klang",
        "pokedex_number": "600",
        "experience_growth": "1059860"
    },
    {
        "name": "Klinklang",
        "pokedex_number": "601",
        "experience_growth": "1059860"
    },
    {
        "name": "Tynamo",
        "pokedex_number": "602",
        "experience_growth": "1250000"
    },
    {
        "name": "Eelektrik",
        "pokedex_number": "603",
        "experience_growth": "1250000"
    },
    {
        "name": "Eelektross",
        "pokedex_number": "604",
        "experience_growth": "1250000"
    },
    {
        "name": "Elgyem",
        "pokedex_number": "605",
        "experience_growth": "1000000"
    },
    {
        "name": "Beheeyem",
        "pokedex_number": "606",
        "experience_growth": "1000000"
    },
    {
        "name": "Litwick",
        "pokedex_number": "607",
        "experience_growth": "1059860"
    },
    {
        "name": "Lampent",
        "pokedex_number": "608",
        "experience_growth": "1059860"
    },
    {
        "name": "Chandelure",
        "pokedex_number": "609",
        "experience_growth": "1059860"
    },
    {
        "name": "Axew",
        "pokedex_number": "610",
        "experience_growth": "1250000"
    },
    {
        "name": "Fraxure",
        "pokedex_number": "611",
        "experience_growth": "1250000"
    },
    {
        "name": "Haxorus",
        "pokedex_number": "612",
        "experience_growth": "1250000"
    },
    {
        "name": "Cubchoo",
        "pokedex_number": "613",
        "experience_growth": "1000000"
    },
    {
        "name": "Beartic",
        "pokedex_number": "614",
        "experience_growth": "1000000"
    },
    {
        "name": "Cryogonal",
        "pokedex_number": "615",
        "experience_growth": "1000000"
    },
    {
        "name": "Shelmet",
        "pokedex_number": "616",
        "experience_growth": "1000000"
    },
    {
        "name": "Accelgor",
        "pokedex_number": "617",
        "experience_growth": "1000000"
    },
    {
        "name": "Stunfisk",
        "pokedex_number": "618",
        "experience_growth": "1000000"
    },
    {
        "name": "Mienfoo",
        "pokedex_number": "619",
        "experience_growth": "1059860"
    },
    {
        "name": "Mienshao",
        "pokedex_number": "620",
        "experience_growth": "1059860"
    },
    {
        "name": "Druddigon",
        "pokedex_number": "621",
        "experience_growth": "1000000"
    },
    {
        "name": "Golett",
        "pokedex_number": "622",
        "experience_growth": "1000000"
    },
    {
        "name": "Golurk",
        "pokedex_number": "623",
        "experience_growth": "1000000"
    },
    {
        "name": "Pawniard",
        "pokedex_number": "624",
        "experience_growth": "1000000"
    },
    {
        "name": "Bisharp",
        "pokedex_number": "625",
        "experience_growth": "1000000"
    },
    {
        "name": "Bouffalant",
        "pokedex_number": "626",
        "experience_growth": "1000000"
    },
    {
        "name": "Rufflet",
        "pokedex_number": "627",
        "experience_growth": "1250000"
    },
    {
        "name": "Braviary",
        "pokedex_number": "628",
        "experience_growth": "1250000"
    },
    {
        "name": "Vullaby",
        "pokedex_number": "629",
        "experience_growth": "1250000"
    },
    {
        "name": "Mandibuzz",
        "pokedex_number": "630",
        "experience_growth": "1250000"
    },
    {
        "name": "Heatmor",
        "pokedex_number": "631",
        "experience_growth": "1000000"
    },
    {
        "name": "Durant",
        "pokedex_number": "632",
        "experience_growth": "1000000"
    },
    {
        "name": "Deino",
        "pokedex_number": "633",
        "experience_growth": "1250000"
    },
    {
        "name": "Zweilous",
        "pokedex_number": "634",
        "experience_growth": "1250000"
    },
    {
        "name": "Hydreigon",
        "pokedex_number": "635",
        "experience_growth": "1250000"
    },
    {
        "name": "Larvesta",
        "pokedex_number": "636",
        "experience_growth": "1250000"
    },
    {
        "name": "Volcarona",
        "pokedex_number": "637",
        "experience_growth": "1250000"
    },
    {
        "name": "Cobalion",
        "pokedex_number": "638",
        "experience_growth": "1250000"
    },
    {
        "name": "Terrakion",
        "pokedex_number": "639",
        "experience_growth": "1250000"
    },
    {
        "name": "Virizion",
        "pokedex_number": "640",
        "experience_growth": "1250000"
    },
    {
        "name": "Tornadus",
        "pokedex_number": "641",
        "experience_growth": "1250000"
    },
    {
        "name": "Thundurus",
        "pokedex_number": "642",
        "experience_growth": "1250000"
    },
    {
        "name": "Reshiram",
        "pokedex_number": "643",
        "experience_growth": "1250000"
    },
    {
        "name": "Zekrom",
        "pokedex_number": "644",
        "experience_growth": "1250000"
    },
    {
        "name": "Landorus",
        "pokedex_number": "645",
        "experience_growth": "1250000"
    },
    {
        "name": "Kyurem",
        "pokedex_number": "646",
        "experience_growth": "1250000"
    },
    {
        "name": "Keldeo",
        "pokedex_number": "647",
        "experience_growth": "1250000"
    },
    {
        "name": "Meloetta",
        "pokedex_number": "648",
        "experience_growth": "1250000"
    },
    {
        "name": "Genesect",
        "pokedex_number": "649",
        "experience_growth": "1250000"
    },
    {
        "name": "Chespin",
        "pokedex_number": "650",
        "experience_growth": "1059860"
    },
    {
        "name": "Quilladin",
        "pokedex_number": "651",
        "experience_growth": "1059860"
    },
    {
        "name": "Chesnaught",
        "pokedex_number": "652",
        "experience_growth": "1059860"
    },
    {
        "name": "Fennekin",
        "pokedex_number": "653",
        "experience_growth": "1059860"
    },
    {
        "name": "Braixen",
        "pokedex_number": "654",
        "experience_growth": "1059860"
    },
    {
        "name": "Delphox",
        "pokedex_number": "655",
        "experience_growth": "1059860"
    },
    {
        "name": "Froakie",
        "pokedex_number": "656",
        "experience_growth": "1059860"
    },
    {
        "name": "Frogadier",
        "pokedex_number": "657",
        "experience_growth": "1059860"
    },
    {
        "name": "Greninja",
        "pokedex_number": "658",
        "experience_growth": "1059860"
    },
    {
        "name": "Bunnelby",
        "pokedex_number": "659",
        "experience_growth": "1000000"
    },
    {
        "name": "Diggersby",
        "pokedex_number": "660",
        "experience_growth": "1000000"
    },
    {
        "name": "Fletchling",
        "pokedex_number": "661",
        "experience_growth": "1059860"
    },
    {
        "name": "Fletchinder",
        "pokedex_number": "662",
        "experience_growth": "1059860"
    },
    {
        "name": "Talonflame",
        "pokedex_number": "663",
        "experience_growth": "1059860"
    },
    {
        "name": "Scatterbug",
        "pokedex_number": "664",
        "experience_growth": "1000000"
    },
    {
        "name": "Spewpa",
        "pokedex_number": "665",
        "experience_growth": "1000000"
    },
    {
        "name": "Vivillon",
        "pokedex_number": "666",
        "experience_growth": "1000000"
    },
    {
        "name": "Litleo",
        "pokedex_number": "667",
        "experience_growth": "1059860"
    },
    {
        "name": "Pyroar",
        "pokedex_number": "668",
        "experience_growth": "1059860"
    },
    {
        "name": "Flab\u00e9b\u00e9",
        "pokedex_number": "669",
        "experience_growth": "1000000"
    },
    {
        "name": "Floette",
        "pokedex_number": "670",
        "experience_growth": "1000000"
    },
    {
        "name": "Florges",
        "pokedex_number": "671",
        "experience_growth": "1000000"
    },
    {
        "name": "Skiddo",
        "pokedex_number": "672",
        "experience_growth": "1000000"
    },
    {
        "name": "Gogoat",
        "pokedex_number": "673",
        "experience_growth": "1000000"
    },
    {
        "name": "Pancham",
        "pokedex_number": "674",
        "experience_growth": "1000000"
    },
    {
        "name": "Pangoro",
        "pokedex_number": "675",
        "experience_growth": "1000000"
    },
    {
        "name": "Furfrou",
        "pokedex_number": "676",
        "experience_growth": "1000000"
    },
    {
        "name": "Espurr",
        "pokedex_number": "677",
        "experience_growth": "1000000"
    },
    {
        "name": "Meowstic",
        "pokedex_number": "678",
        "experience_growth": "1000000"
    },
    {
        "name": "Honedge",
        "pokedex_number": "679",
        "experience_growth": "1000000"
    },
    {
        "name": "Doublade",
        "pokedex_number": "680",
        "experience_growth": "1000000"
    },
    {
        "name": "Aegislash",
        "pokedex_number": "681",
        "experience_growth": "1000000"
    },
    {
        "name": "Spritzee",
        "pokedex_number": "682",
        "experience_growth": "1000000"
    },
    {
        "name": "Aromatisse",
        "pokedex_number": "683",
        "experience_growth": "1000000"
    },
    {
        "name": "Swirlix",
        "pokedex_number": "684",
        "experience_growth": "1000000"
    },
    {
        "name": "Slurpuff",
        "pokedex_number": "685",
        "experience_growth": "1000000"
    },
    {
        "name": "Inkay",
        "pokedex_number": "686",
        "experience_growth": "1000000"
    },
    {
        "name": "Malamar",
        "pokedex_number": "687",
        "experience_growth": "1000000"
    },
    {
        "name": "Binacle",
        "pokedex_number": "688",
        "experience_growth": "1000000"
    },
    {
        "name": "Barbaracle",
        "pokedex_number": "689",
        "experience_growth": "1000000"
    },
    {
        "name": "Skrelp",
        "pokedex_number": "690",
        "experience_growth": "1000000"
    },
    {
        "name": "Dragalge",
        "pokedex_number": "691",
        "experience_growth": "1000000"
    },
    {
        "name": "Clauncher",
        "pokedex_number": "692",
        "experience_growth": "1250000"
    },
    {
        "name": "Clawitzer",
        "pokedex_number": "693",
        "experience_growth": "1250000"
    },
    {
        "name": "Helioptile",
        "pokedex_number": "694",
        "experience_growth": "1000000"
    },
    {
        "name": "Heliolisk",
        "pokedex_number": "695",
        "experience_growth": "1000000"
    },
    {
        "name": "Tyrunt",
        "pokedex_number": "696",
        "experience_growth": "1000000"
    },
    {
        "name": "Tyrantrum",
        "pokedex_number": "697",
        "experience_growth": "1000000"
    },
    {
        "name": "Amaura",
        "pokedex_number": "698",
        "experience_growth": "1000000"
    },
    {
        "name": "Aurorus",
        "pokedex_number": "699",
        "experience_growth": "1000000"
    },
    {
        "name": "Sylveon",
        "pokedex_number": "700",
        "experience_growth": "1000000"
    },
    {
        "name": "Hawlucha",
        "pokedex_number": "701",
        "experience_growth": "1000000"
    },
    {
        "name": "Dedenne",
        "pokedex_number": "702",
        "experience_growth": "1000000"
    },
    {
        "name": "Carbink",
        "pokedex_number": "703",
        "experience_growth": "1250000"
    },
    {
        "name": "Goomy",
        "pokedex_number": "704",
        "experience_growth": "1250000"
    },
    {
        "name": "Sliggoo",
        "pokedex_number": "705",
        "experience_growth": "1250000"
    },
    {
        "name": "Goodra",
        "pokedex_number": "706",
        "experience_growth": "1250000"
    },
    {
        "name": "Klefki",
        "pokedex_number": "707",
        "experience_growth": "800000"
    },
    {
        "name": "Phantump",
        "pokedex_number": "708",
        "experience_growth": "1000000"
    },
    {
        "name": "Trevenant",
        "pokedex_number": "709",
        "experience_growth": "1000000"
    },
    {
        "name": "Pumpkaboo",
        "pokedex_number": "710",
        "experience_growth": "1000000"
    },
    {
        "name": "Gourgeist",
        "pokedex_number": "711",
        "experience_growth": "1000000"
    },
    {
        "name": "Bergmite",
        "pokedex_number": "712",
        "experience_growth": "1000000"
    },
    {
        "name": "Avalugg",
        "pokedex_number": "713",
        "experience_growth": "1000000"
    },
    {
        "name": "Noibat",
        "pokedex_number": "714",
        "experience_growth": "1000000"
    },
    {
        "name": "Noivern",
        "pokedex_number": "715",
        "experience_growth": "1000000"
    },
    {
        "name": "Xerneas",
        "pokedex_number": "716",
        "experience_growth": "1250000"
    },
    {
        "name": "Yveltal",
        "pokedex_number": "717",
        "experience_growth": "1250000"
    },
    {
        "name": "Zygarde",
        "pokedex_number": "718",
        "experience_growth": "1250000"
    },
    {
        "name": "Diancie",
        "pokedex_number": "719",
        "experience_growth": "1250000"
    },
    {
        "name": "Hoopa",
        "pokedex_number": "720",
        "experience_growth": "1250000"
    },
    {
        "name": "Volcanion",
        "pokedex_number": "721",
        "experience_growth": "1250000"
    },
    {
        "name": "Rowlet",
        "pokedex_number": "722",
        "experience_growth": "1059860"
    },
    {
        "name": "Dartrix",
        "pokedex_number": "723",
        "experience_growth": "1059860"
    },
    {
        "name": "Decidueye",
        "pokedex_number": "724",
        "experience_growth": "1059860"
    },
    {
        "name": "Litten",
        "pokedex_number": "725",
        "experience_growth": "1059860"
    },
    {
        "name": "Torracat",
        "pokedex_number": "726",
        "experience_growth": "1059860"
    },
    {
        "name": "Incineroar",
        "pokedex_number": "727",
        "experience_growth": "1059860"
    },
    {
        "name": "Popplio",
        "pokedex_number": "728",
        "experience_growth": "1059860"
    },
    {
        "name": "Brionne",
        "pokedex_number": "729",
        "experience_growth": "1059860"
    },
    {
        "name": "Primarina",
        "pokedex_number": "730",
        "experience_growth": "1059860"
    },
    {
        "name": "Pikipek",
        "pokedex_number": "731",
        "experience_growth": "1000000"
    },
    {
        "name": "Trumbeak",
        "pokedex_number": "732",
        "experience_growth": "1000000"
    },
    {
        "name": "Toucannon",
        "pokedex_number": "733",
        "experience_growth": "1000000"
    },
    {
        "name": "Yungoos",
        "pokedex_number": "734",
        "experience_growth": "1000000"
    },
    {
        "name": "Gumshoos",
        "pokedex_number": "735",
        "experience_growth": "1000000"
    },
    {
        "name": "Grubbin",
        "pokedex_number": "736",
        "experience_growth": "1000000"
    },
    {
        "name": "Charjabug",
        "pokedex_number": "737",
        "experience_growth": "1000000"
    },
    {
        "name": "Vikavolt",
        "pokedex_number": "738",
        "experience_growth": "1000000"
    },
    {
        "name": "Crabrawler",
        "pokedex_number": "739",
        "experience_growth": "1000000"
    },
    {
        "name": "Crabominable",
        "pokedex_number": "740",
        "experience_growth": "1000000"
    },
    {
        "name": "Oricorio",
        "pokedex_number": "741",
        "experience_growth": "1000000"
    },
    {
        "name": "Cutiefly",
        "pokedex_number": "742",
        "experience_growth": "1000000"
    },
    {
        "name": "Ribombee",
        "pokedex_number": "743",
        "experience_growth": "1000000"
    },
    {
        "name": "Rockruff",
        "pokedex_number": "744",
        "experience_growth": "1000000"
    },
    {
        "name": "Lycanroc",
        "pokedex_number": "745",
        "experience_growth": "1000000"
    },
    {
        "name": "Wishiwashi",
        "pokedex_number": "746",
        "experience_growth": "800000"
    },
    {
        "name": "Mareanie",
        "pokedex_number": "747",
        "experience_growth": "1000000"
    },
    {
        "name": "Toxapex",
        "pokedex_number": "748",
        "experience_growth": "1000000"
    },
    {
        "name": "Mudbray",
        "pokedex_number": "749",
        "experience_growth": "1000000"
    },
    {
        "name": "Mudsdale",
        "pokedex_number": "750",
        "experience_growth": "1000000"
    },
    {
        "name": "Dewpider",
        "pokedex_number": "751",
        "experience_growth": "1000000"
    },
    {
        "name": "Araquanid",
        "pokedex_number": "752",
        "experience_growth": "1000000"
    },
    {
        "name": "Fomantis",
        "pokedex_number": "753",
        "experience_growth": "1000000"
    },
    {
        "name": "Lurantis",
        "pokedex_number": "754",
        "experience_growth": "1000000"
    },
    {
        "name": "Morelull",
        "pokedex_number": "755",
        "experience_growth": "1000000"
    },
    {
        "name": "Shiinotic",
        "pokedex_number": "756",
        "experience_growth": "1000000"
    },
    {
        "name": "Salandit",
        "pokedex_number": "757",
        "experience_growth": "1000000"
    },
    {
        "name": "Salazzle",
        "pokedex_number": "758",
        "experience_growth": "1000000"
    },
    {
        "name": "Stufful",
        "pokedex_number": "759",
        "experience_growth": "1000000"
    },
    {
        "name": "Bewear",
        "pokedex_number": "760",
        "experience_growth": "1000000"
    },
    {
        "name": "Bounsweet",
        "pokedex_number": "761",
        "experience_growth": "1059860"
    },
    {
        "name": "Steenee",
        "pokedex_number": "762",
        "experience_growth": "1059860"
    },
    {
        "name": "Tsareena",
        "pokedex_number": "763",
        "experience_growth": "1059860"
    },
    {
        "name": "Comfey",
        "pokedex_number": "764",
        "experience_growth": "800000"
    },
    {
        "name": "Oranguru",
        "pokedex_number": "765",
        "experience_growth": "1250000"
    },
    {
        "name": "Passimian",
        "pokedex_number": "766",
        "experience_growth": "1250000"
    },
    {
        "name": "Wimpod",
        "pokedex_number": "767",
        "experience_growth": "1000000"
    },
    {
        "name": "Golisopod",
        "pokedex_number": "768",
        "experience_growth": "1000000"
    },
    {
        "name": "Sandygast",
        "pokedex_number": "769",
        "experience_growth": "1000000"
    },
    {
        "name": "Palossand",
        "pokedex_number": "770",
        "experience_growth": "1000000"
    },
    {
        "name": "Pyukumuku",
        "pokedex_number": "771",
        "experience_growth": "800000"
    },
    {
        "name": "Type: Null",
        "pokedex_number": "772",
        "experience_growth": "1250000"
    },
    {
        "name": "Silvally",
        "pokedex_number": "773",
        "experience_growth": "1250000"
    },
    {
        "name": "Minior",
        "pokedex_number": "774",
        "experience_growth": "1059860"
    },
    {
        "name": "Komala",
        "pokedex_number": "775",
        "experience_growth": "1250000"
    },
    {
        "name": "Turtonator",
        "pokedex_number": "776",
        "experience_growth": "1000000"
    },
    {
        "name": "Togedemaru",
        "pokedex_number": "777",
        "experience_growth": "1000000"
    },
    {
        "name": "Mimikyu",
        "pokedex_number": "778",
        "experience_growth": "1000000"
    },
    {
        "name": "Bruxish",
        "pokedex_number": "779",
        "experience_growth": "1000000"
    },
    {
        "name": "Drampa",
        "pokedex_number": "780",
        "experience_growth": "1000000"
    },
    {
        "name": "Dhelmise",
        "pokedex_number": "781",
        "experience_growth": "1000000"
    },
    {
        "name": "Jangmo-o",
        "pokedex_number": "782",
        "experience_growth": "1250000"
    },
    {
        "name": "Hakamo-o",
        "pokedex_number": "783",
        "experience_growth": "1250000"
    },
    {
        "name": "Kommo-o",
        "pokedex_number": "784",
        "experience_growth": "1250000"
    },
    {
        "name": "Tapu Koko",
        "pokedex_number": "785",
        "experience_growth": "1250000"
    },
    {
        "name": "Tapu Lele",
        "pokedex_number": "786",
        "experience_growth": "1250000"
    },
    {
        "name": "Tapu Bulu",
        "pokedex_number": "787",
        "experience_growth": "1250000"
    },
    {
        "name": "Tapu Fini",
        "pokedex_number": "788",
        "experience_growth": "1250000"
    },
    {
        "name": "Cosmog",
        "pokedex_number": "789",
        "experience_growth": "1250000"
    },
    {
        "name": "Cosmoem",
        "pokedex_number": "790",
        "experience_growth": "1250000"
    },
    {
        "name": "Solgaleo",
        "pokedex_number": "791",
        "experience_growth": "1250000"
    },
    {
        "name": "Lunala",
        "pokedex_number": "792",
        "experience_growth": "1250000"
    },
    {
        "name": "Nihilego",
        "pokedex_number": "793",
        "experience_growth": "1250000"
    },
    {
        "name": "Buzzwole",
        "pokedex_number": "794",
        "experience_growth": "1250000"
    },
    {
        "name": "Pheromosa",
        "pokedex_number": "795",
        "experience_growth": "1250000"
    },
    {
        "name": "Xurkitree",
        "pokedex_number": "796",
        "experience_growth": "1250000"
    },
    {
        "name": "Celesteela",
        "pokedex_number": "797",
        "experience_growth": "1250000"
    },
    {
        "name": "Kartana",
        "pokedex_number": "798",
        "experience_growth": "1250000"
    },
    {
        "name": "Guzzlord",
        "pokedex_number": "799",
        "experience_growth": "1250000"
    },
    {
        "name": "Necrozma",
        "pokedex_number": "800",
        "experience_growth": "1250000"
    },
    {
        "name": "Magearna",
        "pokedex_number": "801",
        "experience_growth": "1250000"
    }
]